morningscraper/__init__.py
MorningScraper-0.1.dist-info/DESCRIPTION.rst
MorningScraper-0.1.dist-info/top_level.txt
MorningScraper-0.1.dist-info/METADATA
MorningScraper-0.1.dist-info/metadata.json
MorningScraper-0.1.dist-info/WHEEL
MorningScraper-0.1.dist-info/.PKG-INFO.swp
MorningScraper-0.1.dist-info/RECORD
