Metadata-Version: 2.0
Name: MorningScraper
Version: 0.1
Summary: Simple scraper for morningstar.co.uk
Home-page: https://github.com/tobes/MorningScraper
Author: Toby Dacre
Author-email: toby.junk@gmail.com
License: LGPLv2
Keywords: morningstar
Platform: UNKNOWN
Classifier: Development Status :: 3 - Alpha
Classifier: Topic :: Utilities
Classifier: License :: OSI Approved :: GNU Lesser General Public License v2 (LGPLv2)
Classifier: Programming Language :: Python :: 2.7
Classifier: Programming Language :: Python :: 3
Requires-Dist: beautifulsoup4
